ikcode_gtconnect/__init__.py
ikcode_gtconnect/__main__.py
ikcode_gtconnect/ikcode.png
ikcode_gtconnect/main.py
ikcode_gtconnect-1.7.6.dist-info/licenses/LICENSE
ikcode_gtconnect-1.7.6.dist-info/METADATA
ikcode_gtconnect-1.7.6.dist-info/WHEEL
ikcode_gtconnect-1.7.6.dist-info/entry_points.txt
ikcode_gtconnect-1.7.6.dist-info/top_level.txt
ikcode_gtconnect-1.7.6.dist-info/RECORD
