Metadata-Version: 2.4
Name: ikcode-gtconnect
Version: 1.7.6
Summary: IKcode - GUI Terminal Connector
Author: IKcode
Author-email: ikcode.offical@gmail.com
License: MIT
Classifier: Programming Language :: Python :: 3
Classifier: License :: OSI Approved :: MIT License
Classifier: Operating System :: OS Independent
Requires-Python: >=3.7
License-File: LICENSE
Requires-Dist: pyqt5
Dynamic: author
Dynamic: author-email
Dynamic: classifier
Dynamic: license
Dynamic: license-file
Dynamic: requires-dist
Dynamic: requires-python
Dynamic: summary
